ctyun_zos_sdk/__init__.py
ctyun_zos_sdk/async_client.py
ctyun_zos_sdk/client.py
ctyun_zos_sdk/config.py
ctyun_zos_sdk/exceptions.py
ctyun_zos_sdk/session.py
ctyun_zos_sdk-0.1.2.dist-info/licenses/LICENSE
ctyun_zos_sdk-0.1.2.dist-info/METADATA
ctyun_zos_sdk-0.1.2.dist-info/WHEEL
ctyun_zos_sdk-0.1.2.dist-info/top_level.txt
ctyun_zos_sdk-0.1.2.dist-info/RECORD
