Metadata-Version: 2.4
Name: ctyun-zos-sdk
Version: 0.1.2
Summary: A boto3-compatible SDK for CTyun Object Storage (ZOS) with httpx backend
Author: Liu Xin
License: MIT
Project-URL: Homepage, https://e.gitee.com/zgcai/repos/zgcai/ctyun-zos-sdk
Project-URL: Repository, https://e.gitee.com/zgcai/repos/zgcai/ctyun-zos-sdk
Project-URL: Documentation, https://e.gitee.com/zgcai/repos/zgcai/ctyun-zos-sdk/blob/master/README.md
Project-URL: Issues, https://e.gitee.com/zgcai/repos/zgcai/ctyun-zos-sdk/issues/table
Keywords: ctyun,zos,object-storage,s3,boto3,httpx
Classifier: Development Status :: 3 - Alpha
Classifier: Intended Audience :: Developers
Classifier: License :: OSI Approved :: MIT License
Classifier: Programming Language :: Python :: 3
Classifier: Programming Language :: Python :: 3.8
Classifier: Programming Language :: Python :: 3.9
Classifier: Programming Language :: Python :: 3.10
Classifier: Programming Language :: Python :: 3.11
Classifier: Programming Language :: Python :: 3.12
Classifier: Topic :: Internet :: WWW/HTTP
Classifier: Topic :: Software Development :: Libraries :: Python Modules
Requires-Python: >=3.8
License-File: LICENSE
Requires-Dist: httpx>=0.24.0
Requires-Dist: botocore>=1.29.0
Requires-Dist: boto3>=1.26.0
Provides-Extra: dev
Requires-Dist: pytest>=7.0.0; extra == "dev"
Requires-Dist: pytest-asyncio>=0.21.0; extra == "dev"
Requires-Dist: pytest-cov>=4.0.0; extra == "dev"
Requires-Dist: black>=23.0.0; extra == "dev"
Requires-Dist: isort>=5.12.0; extra == "dev"
Requires-Dist: flake8>=6.0.0; extra == "dev"
Requires-Dist: mypy>=1.0.0; extra == "dev"
Dynamic: license-file
